gerlida_cpf/__init__.py
gerlida_cpf/gera_cpf/__init__.py
gerlida_cpf/gera_cpf/gerador_cpf.py
gerlida_cpf/valida_cpf/__init__.py
gerlida_cpf/valida_cpf/validacpf.py
gerlida_cpf-0.0.3.dist-info/METADATA
gerlida_cpf-0.0.3.dist-info/WHEEL
gerlida_cpf-0.0.3.dist-info/top_level.txt
gerlida_cpf-0.0.3.dist-info/RECORD
