Metadata-Version: 2.1
Name: gerlida-cpf
Version: 0.0.3
Summary: Gerador e verificador de CPFs
Home-page: https://github.com/renatolage/dio-bootcamp-unimed-data-science
Author: Renato Lage
Author-email: renato.lage85@gmail.com
License: UNKNOWN
Platform: UNKNOWN
Requires-Python: >=3.8
